setup.cfg
setup.py
test/test_conforms.py
zinspect/__init__.py
zinspect/exceptions.py
zinspect/inspect.py
zinspect.egg-info/PKG-INFO
zinspect.egg-info/SOURCES.txt
zinspect.egg-info/dependency_links.txt
zinspect.egg-info/not-zip-safe
zinspect.egg-info/requires.txt
zinspect.egg-info/top_level.txt
