Metadata-Version: 1.0
Name: zinspect
Version: 0.2.0
Summary: 'Interface enforcement'
Home-page: ''
Author: 'Florent Aide'
Author-email: 'florent.aide@gmail.com'
License: 'PSF'
Download-URL: http://cheeseshop.python.org/packages/2.5/z/zinspect/zinspect-0.2.0-py2.5.egg
Platform: UNKNOWN
Classifier: Development Status :: 3 - Alpha
Classifier: Operating System :: OS Independent
Classifier: Programming Language :: Python
Classifier: License :: OSI Approved :: MIT License
Classifier: Topic :: Software Development :: Libraries :: Python Modules
